{
	"name": "Until Activity Pipeline",
	"properties": {
		"description": "it will check first if file is present then after that it will start the copy activity.",
		"activities": [
			{
				"name": "Until1",
				"type": "Until",
				"dependsOn": [],
				"userProperties": [],
				"typeProperties": {
					"expression": {
						"value": "@bool(activity('Get Metadata1').output.exists)",
						"type": "Expression"
					},
					"activities": [
						{
							"name": "Get Metadata1",
							"type": "GetMetadata",
							"dependsOn": [],
							"policy": {
								"timeout": "7.00:00:00",
								"retry": 0,
								"retryIntervalInSeconds": 30,
								"secureOutput": false,
								"secureInput": false
							},
							"userProperties": [],
							"typeProperties": {
								"dataset": {
									"referenceName": "inputdataset",
									"type": "DatasetReference"
								},
								"fieldList": [
									"exists"
								],
								"storeSettings": {
									"type": "AzureBlobFSReadSettings",
									"enablePartitionDiscovery": false
								},
								"formatSettings": {
									"type": "BinaryReadSettings"
								}
							}
						},
						{
							"name": "If Condition1",
							"type": "IfCondition",
							"dependsOn": [
								{
									"activity": "Get Metadata1",
									"dependencyConditions": [
										"Succeeded"
									]
								}
							],
							"userProperties": [],
							"typeProperties": {
								"expression": {
									"value": "@bool(activity('Get Metadata1').output.exists)",
									"type": "Expression"
								},
								"ifFalseActivities": [
									{
										"name": "Wait1",
										"type": "Wait",
										"dependsOn": [],
										"userProperties": [],
										"typeProperties": {
											"waitTimeInSeconds": 120
										}
									}
								],
								"ifTrueActivities": [
									{
										"name": "Set variable1",
										"type": "SetVariable",
										"dependsOn": [],
										"userProperties": [],
										"typeProperties": {
											"variableName": "FileAvailable",
											"value": "true"
										}
									}
								]
							}
						}
					],
					"timeout": "7.00:00:00"
				}
			},
			{
				"name": "Copy data1",
				"type": "Copy",
				"dependsOn": [
					{
						"activity": "Until1",
						"dependencyConditions": [
							"Succeeded"
						]
					}
				],
				"policy": {
					"timeout": "7.00:00:00",
					"retry": 0,
					"retryIntervalInSeconds": 30,
					"secureOutput": false,
					"secureInput": false
				},
				"userProperties": [],
				"typeProperties": {
					"source": {
						"type": "BinarySource",
						"storeSettings": {
							"type": "AzureBlobFSReadSettings",
							"recursive": true
						},
						"formatSettings": {
							"type": "BinaryReadSettings"
						}
					},
					"sink": {
						"type": "BinarySink",
						"storeSettings": {
							"type": "AzureBlobFSWriteSettings"
						}
					},
					"enableStaging": false
				},
				"inputs": [
					{
						"referenceName": "inputdataset",
						"type": "DatasetReference"
					}
				],
				"outputs": [
					{
						"referenceName": "outputdataset",
						"type": "DatasetReference"
					}
				]
			}
		],
		"variables": {
			"FileAvailable": {
				"type": "String",
				"defaultValue": "false"
			}
		},
		"annotations": []
	}
}